addtopath/__init__.py
addtopath/__main__.py
addtopath/argparsing.py
addtopath/entrypoint.py
addtopath-1.2.0.dist-info/LICENSE
addtopath-1.2.0.dist-info/METADATA
addtopath-1.2.0.dist-info/WHEEL
addtopath-1.2.0.dist-info/entry_points.txt
addtopath-1.2.0.dist-info/top_level.txt
addtopath-1.2.0.dist-info/RECORD
