Metadata-Version: 2.1
Name: addtopath
Version: 1.2.0
Summary: CLI tool for adding things to the PATH on Windows
Home-page: UNKNOWN
Author: Sam McCormack
Author-email: cabbagedevelopment@gmail.com
License: UNKNOWN
Project-URL: Source, https://github.com/CabbageDevelopment/add-to-path
Keywords: cli tool path windows
Platform: UNKNOWN
Classifier: Development Status :: 4 - Beta
Classifier: Intended Audience :: Developers
Classifier: License :: OSI Approved :: MIT License
Requires-Python: ~=3.6
